reloadly_giftcard/giftcard/sdk/Filter/OperatorFilter.py
reloadly_giftcard/giftcard/sdk/Filter/TransactionHistoryFilter.py
reloadly_giftcard/giftcard/sdk/Internal/FxRateRequest.py
reloadly_giftcard/giftcard/sdk/client/GiftcardAPI.py
reloadly_giftcard/giftcard/sdk/dto/Phone.py
reloadly_giftcard/giftcard/sdk/dto/Response/Brand.py
reloadly_giftcard/giftcard/sdk/dto/Response/Country.py
reloadly_giftcard/giftcard/sdk/dto/Response/Discount.py
reloadly_giftcard/giftcard/sdk/dto/Response/FxRate.py
reloadly_giftcard/giftcard/sdk/dto/Response/OperatorFxRate.py
reloadly_giftcard/giftcard/sdk/dto/Response/PinDetail.py
reloadly_giftcard/giftcard/sdk/dto/Response/Products.py
reloadly_giftcard/giftcard/sdk/dto/Response/RedeemInstructions.py
reloadly_giftcard/giftcard/sdk/dto/Response/SimplifiedCountry.py
reloadly_giftcard/giftcard/sdk/dto/Response/SimplifiedProduct.py
reloadly_giftcard/giftcard/sdk/dto/Response/Transaction.py
reloadly_giftcard/giftcard/sdk/enums/DenominationType.py
reloadly_giftcard/giftcard/sdk/operation/BaseGiftCardOperation.py
reloadly_giftcard/giftcard/sdk/operation/DiscountOperations.py
reloadly_giftcard/giftcard/sdk/operation/OrderOperations.py
reloadly_giftcard/giftcard/sdk/operation/ProductOperations.py
reloadly_giftcard/giftcard/sdk/operation/RedeemOperations.py
reloadly_giftcard/giftcard/sdk/operation/ReportOperations.py
reloadly_giftcard/giftcard/sdk/operation/TransactionHistoryOperations.py
reloadly_giftcard/giftcard/tests/GiftCardAPIMockServer.py
reloadly_giftcard/giftcard/tests/client/test_GiftcardAPI.py
reloadly_giftcard/giftcard/tests/operation/test_GiftCardDiscountOperations.py
reloadly_giftcard/giftcard/tests/operation/test_GiftCardOrderOperations.py
reloadly_giftcard/giftcard/tests/operation/test_GiftCardTransactionHistoryOperations.py
reloadly_giftcard/giftcard/tests/operation/test_ProductOperations.py
reloadly_giftcard/giftcard/tests/operation/test_RedeemOperations.py
reloadly_giftcard/giftcard/tests/util/RecordedRequestMatcher.py
reloadly_giftcard-1.1.1.dist-info/METADATA
reloadly_giftcard-1.1.1.dist-info/WHEEL
reloadly_giftcard-1.1.1.dist-info/top_level.txt
reloadly_giftcard-1.1.1.dist-info/RECORD
